Metadata-Version: 2.1
Name: bytepilot-0.0.15
Version: 99.7
Summary: x
Author: x
Author-email: xxx@outlook.com
Requires-Dist: requests
